rin/__init__.py
rin/client.py
rin/gateway/__init__.py
rin/gateway/event.py
rin/gateway/handler.py
rin/gateway/parser.py
rin/gateway/ratelimiter.py
rin/models/__init__.py
rin/models/assets/__init__.py
rin/models/assets/file.py
rin/models/base.py
rin/models/builders/__init__.py
rin/models/builders/ansi.py
rin/models/builders/embed.py
rin/models/builders/intents.py
rin/models/builders/message.py
rin/models/cacheable.py
rin/models/channels/__init__.py
rin/models/channels/text.py
rin/models/channels/types.py
rin/models/guild/__init__.py
rin/models/guild/emoji.py
rin/models/guild/guild.py
rin/models/guild/member.py
rin/models/guild/role.py
rin/models/guild/types.py
rin/models/interactions/__init__.py
rin/models/interactions/interaction.py
rin/models/interactions/types.py
rin/models/message/__init__.py
rin/models/message/components/__init__.py
rin/models/message/components/actionrow.py
rin/models/message/components/button.py
rin/models/message/components/cache.py
rin/models/message/components/modal.py
rin/models/message/components/text.py
rin/models/message/components/types.py
rin/models/message/mentions.py
rin/models/message/message.py
rin/models/message/types.py
rin/models/snowflake.py
rin/models/user.py
rin/py.typed
rin/rest/__init__.py
rin/rest/errors.py
rin/rest/handler.py
rin/rest/ratelimiter.py
rin/typings/__init__.pyi
rin/typings/gateway/__init__.pyi
rin/typings/gateway/payloads.pyi
rin/utils/__init__.py
rin/utils/loop.py
rin-0.1.2.dist-info/LICENSE
rin-0.1.2.dist-info/WHEEL
rin-0.1.2.dist-info/METADATA
rin-0.1.2.dist-info/RECORD
