Metadata-Version: 2.1
Name: rin
Version: 0.1.2
Summary: A successor to the Lefi project
Home-page: https://github.com/an-dyy/Rin
License: MIT
Keywords: discord,discord-api
Author: an-dyy
Author-email: andy.development@protonmail.com
Requires-Python: >=3.9,<4.0
Classifier: License :: OSI Approved :: MIT License
Classifier: Programming Language :: Python :: 3
Classifier: Programming Language :: Python :: 3.10
Classifier: Programming Language :: Python :: 3.9
Requires-Dist: aiohttp (>=3.8.1,<4.0.0)
Requires-Dist: python-magic (>=0.4.25,<0.5.0)
Requires-Dist: typing-extensions (>=4.0.1,<5.0.0)
